yamusicrpc/__init__.py
yamusicrpc/activity_manager.py
yamusicrpc/data.py
yamusicrpc/discord/__init__.py
yamusicrpc/discord/discord_ipc_client.py
yamusicrpc/exceptions.py
yamusicrpc/models/__init__.py
yamusicrpc/models/track_info.py
yamusicrpc/requirements.txt
yamusicrpc/server/__init__.py
yamusicrpc/server/callback.html
yamusicrpc/server/server.py
yamusicrpc/server/server_thread.py
yamusicrpc/yandex/__init__.py
yamusicrpc/yandex/yandex_client.py
yamusicrpc/yandex/yandex_listener.py
yamusicrpc/yandex/yandex_token_receiver.py
yamusicrpc-1.1.1.dist-info/LICENSE
yamusicrpc-1.1.1.dist-info/METADATA
yamusicrpc-1.1.1.dist-info/WHEEL
yamusicrpc-1.1.1.dist-info/RECORD
