Metadata-Version: 2.3
Name: yamusicrpc
Version: 1.1.1
Summary: Python library to share Yandex Music activity to Discord
License: MIT
Keywords: yandex,discord,rich-presence,music,python
Author: Issa Mansur (EDEXADE)
Author-email: issa_mansur@mail.ru
Requires-Python: >=3.9
Classifier: Operating System :: OS Independent
Requires-Dist: aiohttp (>=3.11.18,<4.0.0)
Requires-Dist: flask (>=3.1.1,<4.0.0)
Requires-Dist: pywin32 (>=306,<307) ; sys_platform == "win32"
Requires-Dist: requests (>=2.32.3,<3.0.0)
